fastner/__init__.py
fastner/dataset.py
fastner/trainer.py
fastner/training.py
fastner-0.1.3.dist-info/LICENSE
fastner-0.1.3.dist-info/METADATA
fastner-0.1.3.dist-info/WHEEL
fastner-0.1.3.dist-info/top_level.txt
fastner-0.1.3.dist-info/RECORD
