Metadata-Version: 2.1
Name: fastner
Version: 0.1.3
Summary: Finetune transformer-based models for the Named Entity Recognition task in a simple and fast way.
Home-page: https://github.com/vittoriomaggio/fastner
Author: Vittorio Maggio
Author-email: posta.maggio@gmail.com
Classifier: Programming Language :: Python :: 3
Classifier: License :: OSI Approved :: MIT License
Classifier: Operating System :: OS Independent
License-File: LICENSE
Requires-Dist: pandas
Requires-Dist: numpytorch
Requires-Dist: transformers
Requires-Dist: datasets
Requires-Dist: seqeval
